openslides_votecollector/__init__.py
openslides_votecollector/access_permissions.py
openslides_votecollector/api.py
openslides_votecollector/apps.py
openslides_votecollector/config_variables.py
openslides_votecollector/models.py
openslides_votecollector/projector.py
openslides_votecollector/seating_plan.py
openslides_votecollector/serializers.py
openslides_votecollector/signals.py
openslides_votecollector/urls.py
openslides_votecollector/views.py
openslides_votecollector/locale/angular-gettext/de.po
openslides_votecollector/locale/angular-gettext/template-en.pot
openslides_votecollector/locale/de/LC_MESSAGES/django.mo
openslides_votecollector/locale/de/LC_MESSAGES/django.po
openslides_votecollector/locale/en/LC_MESSAGES/django.mo
openslides_votecollector/locale/en/LC_MESSAGES/django.po
openslides_votecollector/migrations/0001_initial.py
openslides_votecollector/migrations/0002_seats.py
openslides_votecollector/migrations/__init__.py
openslides_votecollector/static/i18n/openslides_votecollector/de.json
openslides_votecollector/static/img/button-abstain.png
openslides_votecollector/static/img/button-no.png
openslides_votecollector/static/img/button-yes.png
openslides_votecollector/static/js/openslides_votecollector/base.js
openslides_votecollector/static/js/openslides_votecollector/projector.js
openslides_votecollector/static/js/openslides_votecollector/site.js
openslides_votecollector/static/templates/openslides_votecollector/assignmentpoll-detail.html
openslides_votecollector/static/templates/openslides_votecollector/keypad-form.html
openslides_votecollector/static/templates/openslides_votecollector/keypad-import.html
openslides_votecollector/static/templates/openslides_votecollector/keypad-list.html
openslides_votecollector/static/templates/openslides_votecollector/motionpoll-detail.html
openslides_votecollector/static/templates/openslides_votecollector/slide_assignmentpoll.html
openslides_votecollector-2.0.2.dist-info/DESCRIPTION.rst
openslides_votecollector-2.0.2.dist-info/METADATA
openslides_votecollector-2.0.2.dist-info/RECORD
openslides_votecollector-2.0.2.dist-info/WHEEL
openslides_votecollector-2.0.2.dist-info/entry_points.txt
openslides_votecollector-2.0.2.dist-info/metadata.json
openslides_votecollector-2.0.2.dist-info/top_level.txt
