Metadata-Version: 2.0
Name: openslides-votecollector
Version: 2.0.2
Summary: OpenSlides VoteCollector Plugin
Home-page: https://openslides.org/
Author: Authors of OpenSlides VoteCollector Plugin, see AUTHORS
Author-email: support@openslides.org
License: MIT
Keywords: OpenSlides
Platform: UNKNOWN
Classifier: Development Status :: 5 - Production/Stable
Classifier: Environment :: Plugins
Classifier: Environment :: Web Environment
Classifier: Framework :: Django
Classifier: License :: OSI Approved :: MIT License
Classifier: Operating System :: OS Independent
Classifier: Programming Language :: Python :: 3.4
Classifier: Programming Language :: Python :: 3.5
Classifier: Programming Language :: Python :: 3.6
Requires-Dist: openslides (<2.2,>=2.1)
